{"type":"Feature","properties":{"tags":{"ISO3166-1":"BI","ISO3166-1:alpha2":"BI","ISO3166-1:alpha3":"BDI","ISO3166-1:numeric":"108","admin_level":"2","alt_name:ba":"\u0411\u0443\u0440\u0443\u043d\u0434\u0438 \u0420\u0435\u0441\u043f\u0443\u0431\u043b\u0438\u043a\u0430\u04bb\u044b","alt_name:bo":"\u0f56\u0fb7\u0f74\u0f0b\u0f62\u0f74\u0f53\u0f0b\u0f51\u0f72\u0f0d","alt_name:eo":"Burundio","alt_name:es":"Burundi","alt_name:gd":"Buruindi;Burundi","alt_name:is":"\u00dar\u00fand\u00ed","alt_name:li":"Burundi","alt_name:mzn":"\u0628\u0631\u0648\u0646\u062f\u06cc","alt_name:new":"\u092c\u0941\u0930\u0941\u0923\u094d\u0921\u0940","alt_name:nl":"Boeroendi","alt_name:oc":"Borondi","alt_name:pt":"Bur\u00fandi","alt_name:rn":"Urundi","alt_name:sk":"Urundi","alt_name:sw":"Urundi","alt_name:th":"\u0e2d\u0e38\u0e23\u0e38\u0e19\u0e14\u0e35","alt_name:tl":"Urundi","alt_name:zh":"\u84b2\u9686\u5730","boundary":"administrative","flag":"http:\/\/upload.wikimedia.org\/wikipedia\/commons\/5\/50\/Flag_of_Burundi.svg","int_name":"Burundi","name":"Burundi","name:ace":"Burundi","name:af":"Burundi","name:als":"Burundi","name:am":"\u1261\u1229\u1295\u12f2","name:an":"Burundi","name:ar":"\u0628\u0648\u0631\u0648\u0646\u062f\u064a","name:arz":"\u0628\u0648\u0631\u0648\u0646\u062f\u0649","name:ast":"Burundi","name:az":"Burundi","name:azb":"\u0628\u0648\u0631\u0648\u0646\u200c\u062f\u06cc","name:ba":"\u0411\u0443\u0440\u0443\u0301\u043d\u0434\u0438","name:bat-smg":"Burundis","name:bcl":"Burundi","name:be":"\u0411\u0443\u0440\u0443\u0301\u043d\u0434\u0437\u0456","name:be-tarask":"\u0411\u0443\u0440\u0443\u0301\u043d\u0434\u0437\u0456","name:bg":"\u0411\u0443\u0440\u0443\u043d\u0434\u0438","name:bh":"\u092c\u0941\u0930\u0941\u0902\u0921\u0940","name:bjn":"Burundi","name:bm":"Burundi","name:bn":"\u09ac\u09c1\u09b0\u09c1\u09a8\u09cd\u09a1\u09bf","name:bo":"\u0f56\u0f74\u0f0b\u0f62\u0f74\u0f53\u0f0b\u0f4c\u0f72\u0f0d","name:bpy":"\u09ac\u09c1\u09b0\u09c1\u09a8\u09cd\u09a1\u09bf","name:br":"Burundi","name:bs":"Burundi","name:bxr":"\u0411\u0443\u0440\u0443\u043d\u0434\u0438","name:ca":"Burundi","name:cbk-zam":"Burundi","name:cdo":"Burundi","name:ce":"\u0411\u0443\u0440\u0443\u043d\u0434\u0438","name:ceb":"Burundi","name:chr":"\u13cb\u13b7\u13c2\u13d7","name:ckb":"\u0628\u0648\u0631\u0648\u0646\u062f\u06cc","name:crh":"Burundi","name:cs":"Burundi","name:cv":"\u0411\u0443\u0440\u0443\u043d\u0434\u0438","name:cy":"Bwrwndi","name:da":"Burundi","name:de":"Burundi","name:din":"Brundi","name:diq":"Burundi","name:dsb":"Burundi","name:dty":"\u092c\u0941\u0930\u0941\u0928\u094d\u0921\u0940","name:dv":"\u0784\u07aa\u0783\u07aa\u0782\u07b0\u0791\u07a9","name:dz":"\u0f56\u0fb7\u0f74\u0f0b\u0f62\u0f74\u0f53\u0f0b\u0f4c\u0f72","name:ee":"Burundi","name:el":"\u039c\u03c0\u03bf\u03c5\u03c1\u03bf\u03cd\u03bd\u03c4\u03b9","name:en":"Burundi","name:eo":"Burundo","name:es":"Burund\u00ed","name:et":"Burundi","name:eu":"Burundi","name:ext":"Burundi","name:fa":"\u0628\u0648\u0631\u0648\u0646\u062f\u06cc","name:ff":"Burunndi","name:fi":"Burundi","name:fo":"Burundi","name:fr":"Burundi","name:frp":"Burundi","name:frr":"Burundi","name:fy":"Boer\u00fbndy","name:ga":"an Bhur\u00fain","name:gag":"Burundi","name:gd":"Burundaidh","name:gl":"Burundi","name:gn":"Vurundi","name:gom":"\u092c\u0941\u0930\u0941\u0902\u0921\u0940","name:gu":"\u0aac\u0ac1\u0ab0\u0ac1\u0a82\u0aa1\u0ac0","name:gv":"Burundee","name:ha":"Burundi","name:hak":"Burundi","name:haw":"Buruni","name:he":"\u05d1\u05d5\u05e8\u05d5\u05e0\u05d3\u05d9","name:hi":"\u092c\u0941\u0930\u0941\u0923\u094d\u0921\u0940","name:hif":"Burundi","name:hr":"Burundi","name:hsb":"Burundi","name:ht":"Bouroundi","name:hu":"Burundi","name:hy":"\u0532\u0578\u0582\u0580\u0578\u0582\u0576\u0564\u056b","name:ia":"Burundi","name:id":"Burundi","name:ie":"Burundi","name:ig":"Burundi","name:ilo":"Burundi","name:io":"Burundi","name:is":"B\u00far\u00fand\u00ed","name:it":"Burundi","name:ja":"\u30d6\u30eb\u30f3\u30b8","name:jam":"Burundi","name:jbo":"burundis","name:jv":"Burundi","name:ka":"\u10d1\u10e3\u10e0\u10e3\u10dc\u10d3\u10d8","name:kaa":"Burundi","name:kab":"Burundi","name:kbp":"Purundi","name:kg":"Burundi","name:ki":"Burundi","name:kk":"\u0411\u0443\u0440\u0443\u043d\u0434\u0438","name:km":"\u1794\u17ca\u17bc\u179a\u17bb\u1793\u178c\u17b8","name:kn":"\u0cac\u0cc1\u0cb0\u0cc1\u0c82\u0ca1\u0cbf","name:ko":"\ubd80\ub8ec\ub514","name:ks":"\u0628\u0648\u0631\u064e\u0646\u0688\u0650","name:ku":"Burund\u00ee","name:kw":"Burundi","name:ky":"\u0411\u0443\u0440\u0443\u043d\u0434\u0438","name:la":"Burundia","name:lad":"Burundi","name:lb":"Burundi","name:lg":"Burundi","name:li":"Boeroendi","name:lij":"Burundi","name:lmo":"Burundi","name:ln":"Burundi","name:lo":"\u0e9a\u0eb9\u0ea5\u0eb1\u0e99\u0e94\u0eb5","name:lrc":"\u0628\u0648\u0631\u0648\u0646\u062f\u06cc","name:lt":"Burundis","name:ltg":"Burundi","name:lv":"Burundi","name:mg":"Borondy","name:min":"Burundi","name:mk":"\u0411\u0443\u0440\u0443\u043d\u0434\u0438","name:ml":"\u0d2c\u0d31\u0d41\u0d23\u0d4d\u0d1f\u0d3f","name:mn":"\u0411\u0443\u0440\u0443\u043d\u0434\u0438","name:mr":"\u092c\u0941\u0930\u0941\u0902\u0921\u0940","name:mrj":"\u0411\u0443\u0440\u0443\u043d\u0434\u0438","name:ms":"Burundi","name:mt":"Burundi","name:my":"\u1018\u1030\u101b\u103d\u1014\u103a\u1012\u102e\u1014\u102d\u102f\u1004\u103a\u1004\u1036","name:mzn":"\u0628\u0648\u0631\u0648\u0646\u062f\u06cc","name:na":"Burundi","name:nah":"Burundi","name:nan":"Burundi","name:nds":"Burundi","name:ne":"\u092c\u0941\u0930\u0942\u0923\u094d\u0921\u0940","name:new":"\u092c\u0941\u0930\u0941\u0928\u094d\u0921\u0940","name:nl":"Burundi","name:nn":"Burundi","name:no":"Burundi","name:nov":"Burundi","name:nso":"Burundi","name:oc":"Burundi","name:olo":"Burundi","name:om":"Buruundii","name:or":"\u0b2c\u0b41\u0b30\u0b41\u0b23\u0b4d\u0b21\u0b3f","name:os":"\u0411\u0443\u0440\u0443\u0301\u043d\u0434\u0438","name:pa":"\u0a2c\u0a41\u0a30\u0a42\u0a70\u0a21\u0a40","name:pam":"Burundi","name:pap":"Burundi","name:pi":"\u092c\u0941\u0930\u0941\u0902\u0921\u0940","name:pih":"Burundi","name:pl":"Burundi","name:pms":"Burundi","name:pnb":"\u0628\u0631\u0646\u0688\u06cc","name:ps":"\u0628\u0631\u0648\u0646\u0689\u064a","name:pt":"Burundi","name:qu":"Burundi","name:rm":"Burundi","name:rn":"Uburundi","name:ro":"Burundi","name:roa-rup":"Burundi","name:ru":"\u0411\u0443\u0440\u0443\u043d\u0434\u0438","name:rue":"\u0411\u0443\u0440\u0443\u0301\u043d\u0434\u0456","name:rw":"Uburundi","name:sa":"\u092c\u0941\u0930\u0941\u0902\u0921\u0940","name:sah":"\u0411\u0443\u0440\u0443\u043d\u0434\u0438","name:sc":"Burundi","name:scn":"Burunni","name:sco":"Burundi","name:se":"Burundi","name:sg":"Burund\u00efi","name:sh":"Burundi","name:si":"\u0db6\u0dd4\u0dbb\u0dd4\u0db1\u0dca\u0da9\u0dd2","name:sk":"Burundi","name:sl":"Burundi","name:smn":"Burundi","name:sms":"Burundd","name:sn":"Burundi","name:so":"Burundi","name:sq":"Burundi","name:sr":"\u0411\u0443\u0440\u0443\u043d\u0434\u0438","name:ss":"iBurundi","name:st":"Burundi","name:stq":"Burundi","name:su":"Burundi","name:sv":"Burundi","name:sw":"Burundi","name:szl":"Bur\u016fndi","name:ta":"\u0baa\u0bc1\u0bb0\u0bc1\u0ba3\u0bcd\u0b9f\u0bbf","name:te":"\u0c2c\u0c41\u0c30\u0c41\u0c02\u0c21\u0c3f","name:tg":"\u0411\u0443\u0440\u0443\u043d\u0434\u0438","name:th":"\u0e1a\u0e38\u0e23\u0e38\u0e19\u0e14\u0e35","name:ti":"\u1265\u1229\u1295\u12f2","name:tk":"Burundi","name:tl":"Burundi","name:to":"Pelaniti","name:tr":"Burundi","name:ts":"Burundi","name:tt":"\u0411\u0443\u0440\u0443\u0301\u043d\u0434\u0438","name:tzl":"Burund\u00ec","name:udm":"\u0411\u0443\u0440\u0443\u043d\u0434\u0438","name:ug":"\u0628\u06c7\u0631\u06c7\u0646\u062f\u0649","name:uk":"\u0411\u0443\u0440\u0443\u0301\u043d\u0434\u0456","name:ur":"\u0628\u0631\u0648\u0646\u0688\u06cc","name:uz":"Burundi","name:vec":"Burundi","name:vep":"Burundi","name:vi":"Burundi","name:vo":"Rundiy\u00e4n","name:vro":"Burundi","name:wa":"Bouroundi","name:war":"Burundi","name:wo":"Buruundi","name:wuu":"\u5e03\u9686\u8fea","name:xal":"\u0411\u0443\u0440\u0443\u043d\u0434\u0438\u043d","name:xmf":"\u10d1\u10e3\u10e0\u10e3\u10dc\u10d3\u10d8","name:yi":"\u05d1\u05d5\u05e8\u05d5\u05e0\u05d3\u05d9","name:yo":"B\u00f9r\u00fand\u00ec","name:yue":"\u5e03\u9686\u8fea","name:zea":"Burundi","name:zh":"\u5e03\u9686\u8fea \/ \u84b2\u9686\u5730","name:zh-Hans":"\u5e03\u9686\u8fea","name:zh-Hant":"\u84b2\u9686\u5730","name:zh-Hant-CN":"\u5e03\u9686\u8fea","name:zh-Hant-TW":"\u84b2\u9686\u5730","name:zh-Latn-pinyin":"B\u00f9l\u00f3ngd\u00ed","name:zu":"iBurundi","official_name":"Republika y'u Burundi","official_name:af":"Republiek van Burundi","official_name:als":"Republik Burundi","official_name:am":"\u12e8\u1261\u122a\u1295\u12f2 \u122a\u1355\u1265\u120a\u12a8","official_name:an":"Republika y'u Burundi","official_name:ar":"\u062c\u0645\u0647\u0648\u0631\u064a\u0629 \u0628\u0648\u0631\u0648\u0646\u062f\u064a","official_name:ast":"Rep\u00fablica de Burundi","official_name:az":"Burundi Respublikas\u0131","official_name:azb":"\u0628\u0648\u0631\u0648\u0646\u200c\u062f\u06cc \u062c\u0648\u0645\u0647\u0648\u0631\u06cc\u062a\u06cc","official_name:ba":"\u0411\u0443\u0440\u0443\u0301\u043d\u0434\u0438 \u0419\u04e9\u043c\u04bb\u04af\u0440\u0438\u04d9\u0442\u0435","official_name:be":"\u0420\u044d\u0441\u043f\u0443\u0301\u0431\u043b\u0456\u043a\u0430 \u0411\u0443\u0440\u0443\u0301\u043d\u0434\u0437\u0456","official_name:be-tarask":"\u0420\u044d\u0441\u043f\u0443\u0431\u043b\u0456\u043a\u0430 \u0411\u0443\u0440\u0443\u043d\u0434\u0437\u0456","official_name:bg":"\u0420\u0435\u043f\u0443\u0431\u043b\u0438\u043a\u0430 \u0411\u0443\u0440\u0443\u043d\u0434\u0438","official_name:bm":"Burundi ka Fasojamana","official_name:bn":"\u09aa\u09cd\u09b0\u099c\u09be\u09a4\u09a8\u09cd\u09a4\u09cd\u09b0\u09c0 \u09ac\u09c1\u09b0\u09c1\u09a8\u09cd\u09a1\u09bf","official_name:bpy":"\u09aa\u09cd\u09b0\u099c\u09be\u09a4\u09a8\u09cd\u09a4\u09cd\u09b0\u09bf \u09ac\u09c1\u09b0\u09c1\u09a8\u09cd\u09a1\u09bf","official_name:br":"Republik Burundi","official_name:bs":"Republika Burundi","official_name:chr":"\u13cd\u13a6\u13da\u13a9 \u13be\u13bf \u13cb\u13b7\u13c2\u13d7","official_name:ckb":"\u06a9\u06c6\u0645\u0627\u0631\u06cc \u0628\u0648\u0631\u0648\u0646\u062f\u06cc","official_name:crh":"Burundi Cumhuriyeti","official_name:cs":"Burundsk\u00e1 republika","official_name:cv":"\u0411\u0443\u0440\u0443\u043d\u0434\u0438 \u0440\u0435\u0441\u043f\u0443\u0431\u043b\u0438\u043a\u0438","official_name:cy":"Gweriniaeth Bwrwndi","official_name:da":"Republikken Burundi","official_name:de":"Republik Burundi","official_name:dsb":"Republika Burundi","official_name:el":"\u0394\u03b7\u03bc\u03bf\u03ba\u03c1\u03b1\u03c4\u03af\u03b1 \u03c4\u03bf\u03c5 \u039c\u03c0\u03bf\u03c5\u03c1\u03bf\u03cd\u03bd\u03c4\u03b9","official_name:en":"Republic of Burundi","official_name:eo":"Respubliko Burundo","official_name:es":"Rep\u00fablica de Burund\u00ed","official_name:et":"Burundi Vabariik","official_name:eu":"Burundiko Errepublika","official_name:ext":"Rep\u00fabrica de Burundi","official_name:fa":"\u062c\u0645\u0647\u0648\u0631\u06cc \u0628\u0648\u0631\u0648\u0646\u062f\u06cc","official_name:ff":"Ndenndaandi Burunndi","official_name:fi":"Burundin tasavalta","official_name:fo":"Tj\u00f3\u00f0veldi\u00f0 Burundi","official_name:fr":"R\u00e9publique du Burundi","official_name:frr":"Republiik faan Burundi","official_name:gd":"Poblachd Bhurundaidh","official_name:gl":"Rep\u00fablica de Burundi","official_name:gn":"Tet\u00e3 Vurundi","official_name:gv":"Pobblaght Vurundee","official_name:ha":"Jamhuriyar Burundi","official_name:hak":"Burundi Khiung-f\u00f2-koet","official_name:he":"\u05d4\u05e8\u05e4\u05d5\u05d1\u05dc\u05d9\u05e7\u05d4 \u05e9\u05dc \u05d1\u05d5\u05e8\u05d5\u05e0\u05d3\u05d9","official_name:hi":"\u092c\u0941\u0930\u0941\u0928\u094d\u0921\u0940 \u0917\u0923\u0930\u093e\u091c\u094d\u092f","official_name:hif":"Republic of Burundi","official_name:hr":"Republika Burundi","official_name:hsb":"Republika Burundi","official_name:hu":"Burundi K\u00f6zt\u00e1rsas\u00e1g","official_name:hy":"\u0532\u0578\u0582\u0580\u0578\u0582\u0576\u0564\u056b \u0540\u0561\u0576\u0580\u0561\u057a\u0565\u057f\u0578\u0582\u0569\u0575\u0578\u0582\u0576","official_name:ia":"Republica de Burundi","official_name:id":"Republik Burundi","official_name:ilo":"Republika ti Burundi","official_name:io":"Burundi republiko","official_name:it":"Repubblica del Burundi","official_name:ja":"\u30d6\u30eb\u30f3\u30b8\u5171\u548c\u56fd","official_name:jam":"Ripoblik a Burundi","official_name:ka":"\u10d1\u10e3\u10e0\u10e3\u10dc\u10d3\u10d8\u10e1 \u10e0\u10d4\u10e1\u10de\u10e3\u10d1\u10da\u10d8\u10d9\u10d0","official_name:kg":"Repubilika ya Burundi","official_name:kk":"\u0411\u0443\u0440\u0443\u0301\u043d\u0434\u0438 \u0420\u0435\u0441\u043f\u0443\u0301\u0431\u043b\u0438\u043a\u0430\u0441\u044b","official_name:kn":"\u0cac\u0cc1\u0cb0\u0cc1\u0c82\u0ca1\u0cbf \u0c97\u0ca3\u0cb0\u0cbe\u0c9c\u0ccd\u0caf","official_name:ko":"\ubd80\ub8ec\ub514 \uacf5\ud654\uad6d","official_name:ku":"Republika y'Uburundi","official_name:ky":"\u0411\u0443\u0440\u0443\u043d\u0434\u0438 \u0420\u0435\u0441\u043f\u0443\u0431\u043b\u0438\u043a\u0430\u0441\u044b","official_name:la":"Respublica Burundia","official_name:lb":"Republik Burundi","official_name:li":"Rippubliek Boeroendi","official_name:lmo":"Rep\u00fcbliga Burundi","official_name:ln":"Republ\u00edki ya Burundi","official_name:lt":"Burund\u017eio Respublika","official_name:ltg":"Burundu Republika","official_name:lv":"Burundi Republika","official_name:mk":"\u0420\u0435\u043f\u0443\u0431\u043b\u0438\u043a\u0430 \u0411\u0443\u0440\u0443\u043d\u0434\u0438","official_name:ml":"\u0d31\u0d3f\u0d2a\u0d2c\u0d4d\u0d32\u0d3f\u0d15\u0d4d \u0d13\u0d2b\u0d4d \u0d2c\u0d31\u0d41\u0d23\u0d4d\u0d1f\u0d3f","official_name:mn":"\u0411\u04af\u0433\u0434 \u041d\u0430\u0439\u0440\u0430\u043c\u0434\u0430\u0445 \u0411\u0443\u0440\u0443\u043d\u0434\u0438 \u0423\u043b\u0441","official_name:mr":"\u092c\u0941\u0930\u0941\u0902\u0921\u0940\u091a\u0947 \u092a\u094d\u0930\u091c\u093e\u0938\u0924\u094d\u0924\u093e\u0915","official_name:ms":"Republik Burundi","official_name:mt":"Repubblika tal-Burundi","official_name:my":"\u1018\u1030\u101b\u103d\u1014\u103a\u1012\u102e \u101e\u1019\u1039\u1019\u1010\u1014\u102d\u102f\u1004\u103a\u1004\u1036","official_name:na":"Ripubrikin Burundi","official_name:nah":"Tl\u0101catlahtohc\u0101y\u014dtl in Burundi","official_name:nan":"Burundi Ki\u014dng-h\u00f4-kok","official_name:nds":"Republiek Burundi","official_name:ne":"\u0917\u0923\u0924\u0928\u094d\u0924\u094d\u0930 \u092c\u0941\u0930\u0942\u0923\u094d\u0921\u0940","official_name:new":"\u092c\u0941\u0930\u0941\u0923\u094d\u0921\u0940 \u0917\u0923\u0930\u093e\u091c\u094d\u092f","official_name:nl":"Republiek Burundi","official_name:nn":"Republikk Burundi","official_name:no":"Republikken Burundi","official_name:nso":"Repabliki ya Burundi","official_name:oc":"Republica de Burundi","official_name:olo":"Burundin Tazavaldu","official_name:os":"\u0420\u0435\u0441\u043f\u0443\u0431\u043b\u0438\u043a\u00e6 \u0411\u0443\u0440\u0443\u043d\u0434\u0438","official_name:pa":"\u0a2c\u0a41\u0a30\u0a42\u0a70\u0a21\u0a40 \u0a26\u0a3e \u0a17\u0a23\u0a30\u0a3e\u0a1c","official_name:pl":"Republika Burundi","official_name:pms":"Rep\u00f9blica Burundi","official_name:pt":"Rep\u00fablica do Bur\u00fandi","official_name:qu":"Burundi Ripuwlika","official_name:rn":"Irepuburika y\u2019Uburundi","official_name:ro":"Republica Burundi","official_name:roa-rup":"Republica di Burundi","official_name:ru":"\u0420\u0435\u0441\u043f\u0443\u0431\u043b\u0438\u043a\u0430 \u0411\u0443\u0440\u0443\u043d\u0434\u0438","official_name:rue":"\u0420\u044d\u0441\u043f\u0443\u0301\u0431\u043b\u0456\u043a\u0430 \u0411\u0443\u0440\u0443\u0301\u043d\u0434\u0456","official_name:sah":"\u0411\u0443\u0440\u0443\u043d\u0434\u0438 \u0420\u0435\u0441\u043f\u0443\u0431\u043b\u0438\u043a\u0430\u0442\u0430","official_name:sco":"Republic o Burundi","official_name:se":"Burundi d\u00e1ssev\u00e1ldi","official_name:sg":"K\u00f6d\u00f6r\u00f6s\u00ease t\u00ee Burund\u00efi","official_name:sh":"Republika Burundi","official_name:sk":"Burundsk\u00e1 republika","official_name:sr":"\u0420\u0435\u043f\u0443\u0431\u043b\u0438\u043a\u0430 \u0411\u0443\u0440\u0443\u043d\u0434\u0438","official_name:stq":"Republik Burundi","official_name:su":"R\u00e9publik Burundi","official_name:sv":"Republiken Burundi","official_name:sw":"Jamhuri ya Burundi","official_name:szl":"Republika Bur\u016fndi","official_name:ta":"\u0baa\u0bc1\u0bb0\u0bc1\u0ba3\u0bcd\u0b9f\u0bbf \u0b95\u0bc1\u0b9f\u0bbf\u0baf\u0bb0\u0b9a\u0bc1","official_name:th":"\u0e2a\u0e32\u0e18\u0e32\u0e23\u0e13\u0e23\u0e31\u0e10\u0e1a\u0e38\u0e23\u0e38\u0e19\u0e14\u0e35","official_name:tk":"Burundi Respublikasy","official_name:tl":"Republika ng Burundi","official_name:tr":"Burundi Cumhuriyeti","official_name:tt":"\u0411\u0443\u0440\u0443\u0301\u043d\u0434\u0438 \u0496\u04e9\u043c\u04bb\u04af\u0440\u0438\u044f\u0442\u0435","official_name:udm":"\u0411\u0443\u0440\u0443\u043d\u0434\u0438 \u0420\u0435\u0441\u043f\u0443\u0431\u043b\u0438\u043a\u0430","official_name:ug":"\u0628\u06c7\u0631\u06c7\u0646\u062f\u0649 \u062c\u06c7\u0645\u06be\u06c7\u0631\u0649\u064a\u0649\u062a\u0649","official_name:uk":"\u0420\u0435\u0441\u043f\u0443\u0301\u0431\u043b\u0456\u043a\u0430 \u0411\u0443\u0440\u0443\u0301\u043d\u0434\u0456","official_name:ur":"\u062c\u0645\u06c1\u0648\u0631\u06cc\u06c1 \u0628\u0631\u0648\u0646\u0688\u06cc","official_name:uz":"Burundi Respublikasi","official_name:vec":"Republica del Burundi","official_name:vep":"Burundin Tazovaldkund","official_name:vi":"C\u1ed9ng h\u00f2a Burundi","official_name:vro":"Burundi Vabariik","official_name:war":"Republika han Burundi","official_name:wo":"G\u00e0awu Buruundi","official_name:wuu":"\u84b2\u9686\u5730\u5171\u548c\u56fd","official_name:xal":"\u0411\u0443\u0440\u0443\u043d\u0434\u0438\u043d \u041e\u0440\u043d","official_name:xmf":"\u10d1\u10e3\u10e0\u10e3\u10dc\u10d3\u10d8\u10e8 \u10e0\u10d4\u10e1\u10de\u10e3\u10d1\u10da\u10d8\u10d9\u10d0","official_name:yi":"\u05e8\u05e2\u05e4\u05d5\u05d1\u05dc\u05d9\u05e7 \u05e4\u05d5\u05df \u05d1\u05d5\u05e8\u05d5\u05e0\u05d3\u05d9","official_name:yo":"Orile-ede Olominira ile Burundi","official_name:zh":"\u5e03\u9686\u8fea\u5171\u548c\u570b","official_name:zu":"iRiphabliki weBurundi","old_name:af":"Koninkryk van Burundi","old_name:ca":"Regne de Burundi","old_name:de":"K\u00f6nigreich Burundi","old_name:eo":"Re\u011dlando Burundo","old_name:es":"Reino de Burundi","old_name:is":"Konungsr\u00edki\u00f0 B\u00far\u00fand\u00ed","old_name:it":"Regno del Burundi","old_name:nds":"K\u00f6nigriek Burundi","old_name:nl":"Koninkrijk Burundi","timezone":"Africa\/Bujumbura","type":"boundary","wikidata":"Q967","wikipedia":"rn:Uburundi"},"timestamp":1716078538,"representative_point":{"type":"Point","coordinates":[29.946054759270154,-3.38946475]}},"geometry":{"type":"Polygon","coordinates":[[[29.0407434,-2.7433533],[29.258052,-3.0673869],[29.2272563,-3.8583203],[29.4359507,-4.4490059],[29.7560463,-4.4687014],[30.0421026,-4.2764255],[30.4507683,-3.5606561],[30.8425513,-3.253653],[30.8498462,-2.9795182],[30.4059494,-2.8609729],[30.5436084,-2.4130213],[29.9589851,-2.3273759],[29.9178581,-2.7023213],[29.7235509,-2.8183202],[29.3708863,-2.8397581],[29.1495459,-2.5910944],[29.0407434,-2.7433533]]]}}