{"type":"Feature","properties":{"tags":{"ISO3166-1":"GA","ISO3166-1:alpha2":"GA","ISO3166-1:alpha3":"GAB","ISO3166-1:numeric":"266","admin_level":"2","alt_name:ar":"\u063a\u0627\u0628\u0648\u0646","boundary":"administrative","currency":"XAF","default_language":"fr","flag":"http:\/\/upload.wikimedia.org\/wikipedia\/commons\/0\/04\/Flag_of_Gabon.svg","name":"Gabon","name:af":"Gaboen","name:als":"Gabun","name:am":"\u130b\u1266\u1295","name:an":"Gab\u00f3n","name:ang":"Gabon","name:ar":"\u0627\u0644\u063a\u0627\u0628\u0648\u0646","name:arz":"\u062c\u0627\u0628\u0648\u0646","name:ast":"Gab\u00f3n","name:az":"Qabon","name:ba":"\u0413\u0430\u0431\u043e\u043d","name:bat-smg":"Gabuons","name:bcl":"Gabon","name:be":"\u0413\u0430\u0431\u043e\u043d","name:be-tarask":"\u0413\u0430\u0431\u043e\u043d","name:bg":"\u0413\u0430\u0431\u043e\u043d","name:bjn":"Gabon","name:bm":"Gabon","name:bn":"\u0997\u09be\u09ac\u09a8","name:bo":"\u0f42\u0f7a\u0f0b\u0f56\u0f7c\u0f53\u0f0d","name:bpy":"\u0997\u09cd\u09af\u09be\u09ac\u09a8","name:br":"Gabon","name:bs":"Gabon","name:bxr":"\u0413\u0430\u0431\u043e\u043d","name:ca":"Gabon","name:ce":"\u0413\u0430\u0431\u043e\u043d","name:ceb":"Gabon","name:ckb":"\u06af\u0627\u0628\u06c6\u0646","name:crh":"Gabon","name:cs":"Gabon","name:cv":"\u0413\u0430\u0431\u043e\u043d","name:cy":"Gabon","name:da":"Gabon","name:de":"Gabun","name:diq":"Gabon","name:dsb":"Gabun","name:dv":"\u078e\u07ac\u0784\u07af\u0782\u07b0","name:dz":"\u0f42\u0fb7\u0f7a\u0f0b\u0f56\u0fb7\u0f7c\u0f53","name:el":"\u0393\u03ba\u03b1\u03bc\u03c0\u03cc\u03bd","name:en":"Gabon","name:eo":"Gabono","name:es":"Gab\u00f3n","name:et":"Gabon","name:eu":"Gabon","name:ext":"Gab\u00f3n","name:fa":"\u06af\u0627\u0628\u0646","name:ff":"Gabon","name:fi":"Gabon","name:fr":"Gabon","name:frp":"Gabon","name:fy":"Gabon","name:ga":"An Ghab\u00fain","name:gag":"Gabon","name:gd":"Gabon","name:gl":"Gab\u00f3n","name:gn":"Gav\u00f5","name:gv":"Gabon","name:he":"\u05d2\u05d1\u05d5\u05df","name:hi":"\u0917\u092c\u0949\u0928","name:hif":"Gabon","name:hr":"Gabon","name:hsb":"Gabun","name:ht":"Gabon","name:hu":"Gabon","name:hy":"\u0533\u0561\u0562\u0578\u0576","name:ia":"Gabon","name:id":"Gabon","name:ie":"Gabon","name:ilo":"Gabon","name:io":"Gabon","name:is":"Gabon","name:it":"Gabon","name:ja":"\u30ac\u30dc\u30f3","name:jbo":"gabon","name:jv":"Gabon","name:ka":"\u10d2\u10d0\u10d1\u10dd\u10dc\u10d8","name:kaa":"Gabon","name:kg":"Ngabu","name:ki":"Gabon","name:kk":"\u0413\u0430\u0431\u043e\u043d","name:kn":"\u0c97\u0cac\u0cca\u0ca8\u0ccd","name:ko":"\uac00\ubd09","name:ks":"\u06af\u06cc\u0628\u0627\u0646","name:ku":"Gabon","name:kw":"Gabon","name:la":"Gabonia","name:lb":"Gabun","name:li":"Gabon","name:lij":"Gab\u00f2n","name:lmo":"Gabon","name:ln":"Gab\u0254\u0301","name:lt":"Gabonas","name:lv":"Gabona","name:lzh":"\u52a0\u5f6d","name:mi":"K\u0101pona","name:min":"Gabon","name:mk":"\u0413\u0430\u0431\u043e\u043d","name:ml":"\u0d17\u0d3e\u0d2c\u0d4b\u0d7a","name:mn":"\u0413\u0430\u0431\u043e\u043d","name:mr":"\u0917\u0945\u092c\u0928","name:mrj":"\u0413\u0430\u0431\u043e\u043d","name:ms":"Gabon","name:mt":"Gabon","name:my":"\u1002\u102b\u1018\u103d\u1014\u103a\u1014\u102d\u102f\u1004\u103a\u1004\u1036","name:na":"Gabun","name:nah":"Gabon","name:nan":"Gabon","name:nds":"Gabun","name:nds-nl":"Gabon","name:ne":"\u0917\u093e\u092c\u094b\u0928","name:nl":"Gabon","name:nn":"Gabon","name:no":"Gabon","name:nov":"Gabon","name:nso":"Gabon","name:nv":"Gab\u01eb\u0301\u01eb\u0301","name:oc":"Gabon","name:or":"\u0b17\u0b3e\u0b2c\u0b4b\u0b28","name:os":"\u0413\u0430\u0431\u043e\u043d","name:pa":"\u0a17\u0a2c\u0a3e\u0a28","name:pam":"Gabon","name:pap":"Gabon","name:pdc":"Gabun","name:pih":"Gabon","name:pl":"Gabon","name:pms":"Gab\u00f2n","name:pnb":"\u06af\u06cc\u0628\u0648\u0646","name:ps":"\u06ab\u0627\u0628\u0646","name:pt":"Gab\u00e3o","name:qu":"Gabun","name:rm":"Gabun","name:ro":"Gabon","name:roa-rup":"Gabon","name:ru":"\u0413\u0430\u0431\u043e\u043d","name:rw":"Gabon","name:sa":"\u0917\u093e\u092c\u094b\u0928","name:sah":"\u0413\u0430\u0431\u043e\u043d","name:sc":"Gab\u00f2n","name:scn":"Gabon","name:sco":"Gabon","name:se":"Gabon","name:sg":"Gab\u00f6on","name:sh":"Gabon","name:si":"\u0d9c\u0dd0\u0db6\u0ddc\u0db1\u0dca","name:simple":"Gabon","name:sk":"Gabon","name:sl":"Gabon","name:smn":"Gabon","name:sms":"Gaboon","name:sn":"Gabon","name:so":"Gabon","name:sq":"Gaboni","name:sr":"\u0413\u0430\u0431\u043e\u043d","name:ss":"IGabhoni","name:st":"Gabon","name:stq":"Gabun","name:su":"Gabon","name:sv":"Gabon","name:sw":"Gabon","name:szl":"Gab\u016fn","name:ta":"\u0b95\u0bbe\u0baa\u0bcb\u0ba9\u0bcd","name:te":"\u0c17\u0c2c\u0c3e\u0c28\u0c4d","name:tg":"\u0413\u0430\u0431\u043e\u043d","name:th":"\u0e1b\u0e23\u0e30\u0e40\u0e17\u0e28\u0e01\u0e32\u0e1a\u0e2d\u0e07","name:tk":"Gabon","name:tl":"Gabon","name:tpi":"Gabon","name:tr":"Gabon","name:ts":"Gaboni","name:tt":"\u0413\u0430\u0431\u043e\u043d","name:tzl":"Gabon","name:ug":"\u06af\u0627\u0628\u0648\u0646","name:uk":"\u0413\u0430\u0431\u043e\u043d","name:ur":"\u06af\u06cc\u0628\u0648\u0646","name:uz":"Gabon","name:vec":"Gabon","name:vi":"Gabon","name:vo":"Gabun\u00e4n","name:vro":"Gabon","name:war":"Gabon","name:wo":"Gabo\u014b","name:xal":"\u0413\u0430\u04bb\u0438\u0442\u0443\u0434\u0438\u043d \u041e\u0440\u043d","name:yi":"\u05d2\u05d0\u05d1\u05d0\u05df","name:yo":"G\u00e0b\u1ecd\u0300n","name:yue":"\u52a0\u84ec","name:zea":"Gabon","name:zh":"\u52a0\u84ec","name:zh-Hans":"\u52a0\u84ec","name:zh-Hant":"\u52a0\u84ec \/ \u52a0\u5f6d","name:zh-Hant-CN":"\u52a0\u84ec","name:zh-TW":"\u52a0\u5f6d","name:zu":"IGaboni","official_name:ar":"\u0627\u0644\u062c\u0645\u0647\u0648\u0631\u064a\u0629 \u0627\u0644\u063a\u0627\u0628\u0648\u0646\u064a\u0629","official_name:cs":"Gabonsk\u00e1 republika","official_name:fa":"\u062c\u0645\u0647\u0648\u0631\u06cc \u06af\u0627\u0628\u0646","official_name:gn":"Gav\u00f5 Tavakuairet\u00e3","official_name:pt":"Rep\u00fablica Gabonesa","official_name:zh":"\u52a0\u84ec\u5171\u548c\u56fd \/ \u52a0\u5f6d\u5171\u548c\u570b","official_name:zh-Hans":"\u52a0\u84ec\u5171\u548c\u56fd","official_name:zh-Hant":"\u52a0\u5f6d\u5171\u548c\u570b","timezone":"Africa\/Libreville","type":"boundary","wikidata":"Q1000","wikipedia":"en:Gabon"},"timestamp":1716078538,"representative_point":{"type":"Point","coordinates":[11.519386735248457,-0.9039705]}},"geometry":{"type":"Polygon","coordinates":[[[9.1492944,0.7534473],[9.1031493,0.3669736],[8.5149097,-0.7475144],[9.4732753,-2.5336592],[11.043616,-4.126909],[11.2261139,-3.6997193],[11.487222,-3.511111],[11.683333,-3.694444],[11.925833,-3.636944],[11.974444,-3.316111],[11.701111,-3.178056],[11.804444,-3.013056],[11.532774,-2.8420707],[11.5226841,-2.371747],[11.7240429,-2.550378],[11.931092,-2.3647384],[12.510327,-2.4500624],[12.4417056,-1.8750127],[12.651773,-1.812454],[12.997593,-2.367342],[13.4899664,-2.4352485],[13.761181,-2.082874],[13.86671,-2.467775],[14.101776,-2.51161],[14.259899,-2.340238],[14.151575,-2.2323],[14.242608,-2.010345],[14.435224,-1.90208],[14.528796,-0.613431],[13.842937,-0.18737],[13.955581,0.339861],[14.4914951,0.8472744],[14.1845184,1.3977107],[13.1523192,1.2360752],[13.2948592,2.1705553],[13.1896146,2.2840306],[11.6673845,2.3192896],[11.372882,2.2944801],[11.359111,2.1719355],[11.333325,1.0000253],[9.9519735,0.9219855],[9.6744734,1.0675583],[9.1492944,0.7534473]]]}}